webint_code/__init__.py
webint_code/templates/__init__.py
webint_code/templates/index.html
webint_code/templates/project/commit.html
webint_code/templates/project/commit_log.html
webint_code/templates/project/created.html
webint_code/templates/project/index.html
webint_code/templates/project/issues/create.html
webint_code/templates/project/issues/index.html
webint_code/templates/project/issues/issue.html
webint_code/templates/project/namespace.html
webint_code/templates/project/release.html
webint_code/templates/project/release_file.html
webint_code/templates/project/repository_file.html
webint_code/templates/project/settings.html
webint_code/templates/projects.html
webint_code/templates/pypi/index.html
webint_code/templates/pypi/project.html
webint_code/templates/search/index.html
webint_code/templates/search/results.html
webint_code/templates/snippets/snippet.html
webint_code/templates/system.html
webint_code/templates/template.html
webint_code-0.0.71.dist-info/METADATA
webint_code-0.0.71.dist-info/entry_points.txt
webint_code-0.0.71.dist-info/WHEEL
webint_code-0.0.71.dist-info/RECORD
